pygutz/__init__.py
pygutz/main.py
pygutz/commands/__init__.py
pygutz/commands/cli.py
pygutz/commands/structure.py
pygutz/commands/template.py
pygutz/core/__init__.py
pygutz/core/base.py
pygutz/gen/__init__.py
pygutz/gen/general.py
pygutz/gen/hexproject.py
tests/__init__.py
pygutz-0.1.1.dist-info/LICENSE
pygutz-0.1.1.dist-info/METADATA
pygutz-0.1.1.dist-info/WHEEL
pygutz-0.1.1.dist-info/entry_points.txt
pygutz-0.1.1.dist-info/top_level.txt
pygutz-0.1.1.dist-info/RECORD
