Metadata-Version: 2.1
Name: pygutz
Version: 0.1.1
Author: Nutchapon
Author-email: nutchapon.met1002@gmail.com
Maintainer: Nutchapon
License: MIT
License-File: LICENSE
Requires-Dist: click
Requires-Dist: fastapi[standard]
Requires-Dist: uvicorn
Requires-Dist: SQLAlchemy
Requires-Dist: pydantic
Requires-Dist: pydantic-settings
